{
  "updated_at": "2026-06-11 18:26:10",
  "updated_at_kst": "2026-06-12 03:26:10",
  "source": "https://trends.google.com/trending/rss?geo=KR",
  "topics": [
    {
      "title": "미국",
      "summary": "오늘 급상승 검색어 기반 주제",
      "news_url": "https://news.google.com/search?q=%EB%AF%B8%EA%B5%AD&hl=ko&gl=KR&ceid=KR:ko"
    },
    {
      "title": "fifa world cup 2026 start date",
      "summary": "오늘 급상승 검색어 기반 주제",
      "news_url": "https://news.google.com/search?q=fifa+world+cup+2026+start+date&hl=ko&gl=KR&ceid=KR:ko"
    },
    {
      "title": "기아 pv5",
      "summary": "오늘 급상승 검색어 기반 주제",
      "news_url": "https://news.google.com/search?q=%EA%B8%B0%EC%95%84+pv5&hl=ko&gl=KR&ceid=KR:ko"
    },
    {
      "title": "2026 年 fifa 世界杯",
      "summary": "오늘 급상승 검색어 기반 주제",
      "news_url": "https://news.google.com/search?q=2026+%E5%B9%B4+fifa+%E4%B8%96%E7%95%8C%E6%9D%AF&hl=ko&gl=KR&ceid=KR:ko"
    },
    {
      "title": "이상화",
      "summary": "오늘 급상승 검색어 기반 주제",
      "news_url": "https://news.google.com/search?q=%EC%9D%B4%EC%83%81%ED%99%94&hl=ko&gl=KR&ceid=KR:ko"
    }
  ]
}
