{
  "updated_at": "2026-04-07 16:16:09",
  "updated_at_kst": "2026-04-08 01:16:09",
  "source": "https://trends.google.com/trending/rss?geo=KR",
  "topics": [
    {
      "title": "한일가왕전",
      "summary": "오늘 급상승 검색어 기반 주제",
      "news_url": "https://news.google.com/search?q=%ED%95%9C%EC%9D%BC%EA%B0%80%EC%99%95%EC%A0%84&hl=ko&gl=KR&ceid=KR:ko"
    },
    {
      "title": "해상 운송",
      "summary": "오늘 급상승 검색어 기반 주제",
      "news_url": "https://news.google.com/search?q=%ED%95%B4%EC%83%81+%EC%9A%B4%EC%86%A1&hl=ko&gl=KR&ceid=KR:ko"
    },
    {
      "title": "윤수영",
      "summary": "오늘 급상승 검색어 기반 주제",
      "news_url": "https://news.google.com/search?q=%EC%9C%A4%EC%88%98%EC%98%81&hl=ko&gl=KR&ceid=KR:ko"
    },
    {
      "title": "권혁",
      "summary": "오늘 급상승 검색어 기반 주제",
      "news_url": "https://news.google.com/search?q=%EA%B6%8C%ED%98%81&hl=ko&gl=KR&ceid=KR:ko"
    },
    {
      "title": "avgo",
      "summary": "오늘 급상승 검색어 기반 주제",
      "news_url": "https://news.google.com/search?q=avgo&hl=ko&gl=KR&ceid=KR:ko"
    }
  ]
}
